pytorch_quik/__init__.py
pytorch_quik/api.py
pytorch_quik/arg.py
pytorch_quik/ddp.py
pytorch_quik/dummy.py
pytorch_quik/hugging.py
pytorch_quik/io.py
pytorch_quik/metrics.py
pytorch_quik/mlflow.py
pytorch_quik/tensor.py
pytorch_quik/transform.py
pytorch_quik/travel.py
pytorch_quik/tune.py
pytorch_quik/utils.py
pytorch_quik/tests/__init__.py
pytorch_quik/tests/conftest.py
pytorch_quik/tests/test_api.py
pytorch_quik/tests/test_arg.py
pytorch_quik/tests/test_bert.py
pytorch_quik/tests/test_ddp.py
pytorch_quik/tests/test_io.py
pytorch_quik/tests/test_metrics.py
pytorch_quik/tests/test_mlflow.py
pytorch_quik/tests/test_serve.py
pytorch_quik/tests/test_tensors.py
pytorch_quik/tests/test_transform.py
pytorch_quik/tests/test_travel.py
pytorch_quik/tests/test_trek.py
pytorch_quik/tests/test_tune.py
pytorch_quik/tests/test_utils.py
pytorch_quik-0.3.3.dist-info/METADATA
pytorch_quik-0.3.3.dist-info/WHEEL
pytorch_quik-0.3.3.dist-info/top_level.txt
pytorch_quik-0.3.3.dist-info/RECORD
