Metadata-Version: 2.1
Name: pytorch-quik
Version: 0.3.3
Summary: functions to make working in pytorch quik-er
Home-page: https://github.com/donchesworth/pytorch-quik
Author: Don Chesworth
Author-email: donald.chesworth@gmail.com
License: BSD
Platform: UNKNOWN
Classifier: License :: OSI Approved :: BSD License
Classifier: Programming Language :: Python :: 3.8
Requires-Dist: torch (>=1.7.0)
Requires-Dist: torchvision
Requires-Dist: pandas (>=1.1)
Requires-Dist: transformers
Requires-Dist: sentencepiece
Requires-Dist: imbalanced-learn
Requires-Dist: pytest
Requires-Dist: pytest-cov
Requires-Dist: pytest-mpl
Requires-Dist: pytest-lazy-fixture
Requires-Dist: pytest-dotenv
Requires-Dist: codecov
Requires-Dist: numpy (>=1.21.0)
Requires-Dist: bump2version
Requires-Dist: mlflow
Requires-Dist: boto3
Requires-Dist: ray[tune]
Requires-Dist: torchserve
Requires-Dist: torch-model-archiver
Requires-Dist: ruamel.yaml
